{
  "nodes": [
    { "id": "making_cosmetics", "type": "supplier", "name": "Making Cosmetics", "properties": { "tier": "premium", "specialty": "wholesale_ingredients" } },
    { "id": "lotion_crafter", "type": "supplier", "name": "Lotion Crafter", "properties": { "tier": "bulk", "specialty": "skincare_ingredients" } },
    { "id": "fnwl", "type": "supplier", "name": "From Nature With Love", "properties": { "tier": "specialty", "specialty": "organic_natural" } },
    { "id": "pure_spa_direct", "type": "supplier", "name": "Pure Spa Direct", "properties": { "tier": "distributor", "specialty": "spa_salon_supplies" } },
    { "id": "universal_companies", "type": "supplier", "name": "Universal Companies", "properties": { "tier": "distributor", "specialty": "professional_supplies" } },
    { "id": "ingredi", "type": "supplier", "name": "Ingredi", "properties": { "tier": "bulk", "specialty": "cosmetic_ingredients" } },
    { "id": "hyaluronic_acid", "type": "ingredient", "name": "Hyaluronic Acid", "properties": { "price_per_kg": 459.90, "category": "humectant" } },
    { "id": "vitamin_c", "type": "ingredient", "name": "Vitamin C", "properties": { "price_per_kg": 325.00, "category": "antioxidant" } },
    { "id": "retinol", "type": "ingredient", "name": "Retinol", "properties": { "price_per_kg": 759.95, "category": "anti_aging" } },
    { "id": "niacinamide", "type": "ingredient", "name": "Niacinamide", "properties": { "price_per_kg": 84.22, "category": "vitamin" } },
    { "id": "vitamin_e", "type": "ingredient", "name": "Vitamin E", "properties": { "price_per_kg": 518.55, "category": "antioxidant" } },
    { "id": "sea_kelp_bioferment", "type": "ingredient", "name": "Sea Kelp Bioferment", "properties": { "price_per_kg": 52.50, "category": "bioactive", "availability": "sold_out" } },
    { "id": "snow_mushroom_complex", "type": "ingredient", "name": "Snow Mushroom Complex", "properties": { "price_per_kg": 144.95, "category": "bioactive" } },
    { "id": "luxe_skin_studio", "type": "salon", "name": "Luxe Skin Studio" },
    { "id": "zen_wellness_spa", "type": "salon", "name": "Zen Wellness Spa" },
    { "id": "advanced_derma_clinic", "type": "salon", "name": "Advanced Derma Clinic" },
    { "id": "the_beverly_hills_hotel_spa", "type": "salon", "name": "The Beverly Hills Hotel Spa" },
    { "id": "ciel_spa", "type": "salon", "name": "Ciel Spa" },
    { "id": "facials", "type": "service", "name": "Facials" },
    { "id": "chemical_peels", "type": "service", "name": "Chemical Peels" },
    { "id": "microdermabrasion", "type": "service", "name": "Microdermabrasion" },
    { "id": "body_treatments", "type": "service", "name": "Body Treatments" },
    { "id": "humectant", "type": "category", "name": "Humectant" },
    { "id": "antioxidant", "type": "category", "name": "Antioxidant" },
    { "id": "anti_aging", "type": "category", "name": "Anti-aging" },
    { "id": "vitamin", "type": "category", "name": "Vitamin" },
    { "id": "bioactive", "type": "category", "name": "Bioactive" }
  ],
  "edges": [
    { "source": "making_cosmetics", "target": "hyaluronic_acid" },
    { "source": "making_cosmetics", "target": "vitamin_c" },
    { "source": "lotion_crafter", "target": "retinol" },
    { "source": "lotion_crafter", "target": "vitamin_e" },
    { "source": "lotion_crafter", "target": "sea_kelp_bioferment" },
    { "source": "lotion_crafter", "target": "snow_mushroom_complex" },
    { "source": "fnwl", "target": "niacinamide" },
    { "source": "ingredi", "target": "hyaluronic_acid" },
    { "source": "ingredi", "target": "vitamin_c" },
    { "source": "hyaluronic_acid", "target": "humectant" },
    { "source": "vitamin_c", "target": "antioxidant" },
    { "source": "retinol", "target": "anti_aging" },
    { "source": "niacinamide", "target": "vitamin" },
    { "source": "vitamin_e", "target": "antioxidant" },
    { "source": "sea_kelp_bioferment", "target": "bioactive" },
    { "source": "snow_mushroom_complex", "target": "bioactive" },
    { "source": "luxe_skin_studio", "target": "facials" },
    { "source": "luxe_skin_studio", "target": "chemical_peels" },
    { "source": "zen_wellness_spa", "target": "facials" },
    { "source": "advanced_derma_clinic", "target": "microdermabrasion" },
    { "source": "the_beverly_hills_hotel_spa", "target": "body_treatments" },
    { "source": "ciel_spa", "target": "facials" },
    { "source": "pure_spa_direct", "target": "luxe_skin_studio" },
    { "source": "pure_spa_direct", "target": "the_beverly_hills_hotel_spa" },
    { "source": "universal_companies", "target": "zen_wellness_spa" },
    { "source": "universal_companies", "target": "advanced_derma_clinic" },
    { "source": "universal_companies", "target": "ciel_spa" }
  ]
}
